lynxtray/__init__.py
lynxtray/py.typed
lynxtray/traybar.py
lynxtray/win32_adapter.py
lynxtray-0.2.2.dist-info/METADATA
lynxtray-0.2.2.dist-info/WHEEL
lynxtray-0.2.2.dist-info/licenses/LICENSE
lynxtray-0.2.2.dist-info/RECORD
