Metadata-Version: 2.4
Name: lynxtray
Version: 0.2.2
Summary: Windows system tray icon
Project-URL: Homepage, https://github.com/C0rn3j/lynxtray
Project-URL: Issues, https://github.com/C0rn3j/lynxtray/issues
Author-email: Martin Rys <martin@rys.rs>
License-File: LICENSE
Classifier: Intended Audience :: Developers
Classifier: Intended Audience :: System Administrators
Classifier: License :: OSI Approved :: BSD License
Classifier: Operating System :: OS Independent
Classifier: Programming Language :: Python
Classifier: Programming Language :: Python :: 3
Classifier: Programming Language :: Python :: 3.10
Classifier: Programming Language :: Python :: 3.11
Classifier: Programming Language :: Python :: 3.12
Classifier: Programming Language :: Python :: 3.13
Classifier: Topic :: Software Development :: Libraries :: Python Modules
Classifier: Typing :: Typed
Requires-Python: >=3.10
